tools_cosmo/__init__.py
tools_cosmo/basic_functions.py
tools_cosmo/bias.py
tools_cosmo/calculator.py
tools_cosmo/constants.py
tools_cosmo/cosmo.py
tools_cosmo/cosmo_equations.py
tools_cosmo/emulate_BoltmannSolver.py
tools_cosmo/luminosity_function.py
tools_cosmo/mass_accretion.py
tools_cosmo/massfct.py
tools_cosmo/param.py
tools_cosmo/plotting_function.py
tools_cosmo/run_BoltzmannSolver.py
tools_cosmo/source_model.py
tools_cosmo/input_data/cpl_class_emulator.pkl
toolscosmo/EFT.py
toolscosmo/__init__.py
toolscosmo/_merger_trees.py
toolscosmo/basic_functions.py
toolscosmo/bias.py
toolscosmo/calculator.py
toolscosmo/constants.py
toolscosmo/cosmo.py
toolscosmo/cosmo_equations.py
toolscosmo/cython_ParkinsonColeHelly2008.cpp
toolscosmo/emulate_BoltmannSolver.py
toolscosmo/extreme_value_stats.py
toolscosmo/generate_ic.py
toolscosmo/luminosity_function.py
toolscosmo/mass_accretion.py
toolscosmo/massfct.py
toolscosmo/merger_trees.py
toolscosmo/neural_networks.py
toolscosmo/num_sim_data.py
toolscosmo/param.py
toolscosmo/plotting_function.py
toolscosmo/run_BoltzmannSolver.py
toolscosmo/scipy_func.py
toolscosmo/source_model.py
toolscosmo/input_data/Schneider2018_wdm_hmf.pkl
toolscosmo/input_data/cpl_class_emulator.pkl
toolscosmo-0.1.9.dist-info/LICENSE
toolscosmo-0.1.9.dist-info/METADATA
toolscosmo-0.1.9.dist-info/WHEEL
toolscosmo-0.1.9.dist-info/top_level.txt
toolscosmo-0.1.9.dist-info/RECORD
