Metadata-Version: 2.1
Name: toolscosmo
Version: 0.1.9
Author: Sambit Giri
Author-email: sambit.giri@su.se
License-File: LICENSE
Requires-Dist: cython
Requires-Dist: numpy==1.26.4
Requires-Dist: scipy
Requires-Dist: matplotlib
Requires-Dist: astropy
Requires-Dist: pytest
Requires-Dist: scikit-learn==1.2.0
Requires-Dist: tqdm
Requires-Dist: joblib
Requires-Dist: pandas
Requires-Dist: tools21cm
Requires-Dist: baccoemu
Requires-Dist: camb
Requires-Dist: corecon
Requires-Dist: numba
Requires-Dist: torch
Requires-Dist: torchvision
Requires-Dist: torchaudio
